<DOMSymbolItem xmlns:xsi="http://www.w3.org/2001/XMLSchema-instance" xmlns="http://ns.adobe.com/xfl/2008/" name="Cinema 2 Scene 3 Orb Shatter Piece12" itemID="492d9ecb-00000f0d" sourceFlashFilepath="Rob &amp; Steve Hewitt\My Documents\Super Mario 63\Orb Shattering.fla" sourceLibraryItemHRef="Cinema 2 Scene 3 Orb Shatter Piece12" sourceLastModified="1227726891" lastModified="1227726891" sourceItemID="492d9ecb-00000f0d">
  <timeline>
    <DOMTimeline name="Cinema 2 Scene 3 Orb Shatter Piece12">
      <layers>
        <DOMLayer name="Layer 2" color="#9933CC" current="true" isSelected="true">
          <frames>
            <DOMFrame index="0" keyMode="9728">
              <Actionscript>
                <script><![CDATA[_parent.I(_name);
onEnterFrame = function () {
	_parent.OEF(_name);
};
]]></script>
              </Actionscript>
              <elements/>
            </DOMFrame>
          </frames>
        </DOMLayer>
        <DOMLayer name="Layer 1" color="#4FFF4F">
          <frames>
            <DOMFrame index="0" keyMode="9728">
              <elements>
                <DOMGroup>
                  <members>
                    <DOMShape>
                      <fills>
                        <FillStyle index="1">
                          <RadialGradient>
                            <matrix>
                              <Matrix a="0.04437255859375" d="0.04437255859375" tx="-12.9" ty="-21.7"/>
                            </matrix>
                            <GradientEntry color="#F8F2C2" alpha="0.0823529411764706" ratio="0"/>
                            <GradientEntry color="#FEF7BC" alpha="0.623529411764706" ratio="1"/>
                          </RadialGradient>
                        </FillStyle>
                      </fills>
                      <strokes>
                        <StrokeStyle index="1">
                          <SolidStroke scaleMode="normal" weight="4">
                            <fill>
                              <SolidColor/>
                            </fill>
                          </SolidStroke>
                        </StrokeStyle>
                      </strokes>
                      <edges>
                        <Edge fillStyle1="1" edges="!186 123|49 194!49 194|-186 204!-186 204[-155 178 -116 164!-116 164|-41 109!-41 109|-26 89!-26 89[0 83 -21 84!-21 84|-121 79!-121 79[-178 48 -186 29!-186 29[-181 21 -166 24!-166 24[-108 14 -46 9!-46 9[-31 3 -19 -1!-19 -1[9 -16 24 -41
!24 -41[24 -56 20 -70!20 -70[10 -108 -18 -131!-18 -131[-4 -151 9 -171!9 -171[5 -195 -2 -217!-2 -217|119 -218!119 -218[184 -143 173 -5!173 -5[167 69 186 123"/>
                        <Edge strokeStyle="1" edges="
!186 123[116 179 53 217"/>
                      </edges>
                    </DOMShape>
                  </members>
                </DOMGroup>
              </elements>
            </DOMFrame>
          </frames>
        </DOMLayer>
      </layers>
    </DOMTimeline>
  </timeline>
</DOMSymbolItem>