<DOMSymbolItem xmlns:xsi="http://www.w3.org/2001/XMLSchema-instance" xmlns="http://ns.adobe.com/xfl/2008/" name=" Menu/Bomb-omb Battle Field Mountain" itemID="46e0cd03-00000a67" sourceFlashFilepath="Rob &amp; Steve Hewitt\My Documents\Super Mario 63\New Title Screen Design.fla" sourceLibraryItemHRef="Bomb-omb Battle Field Mountain" sourceLastModified="1189138391" lastModified="1192127052" lastUniqueIdentifier="14" sourceItemID="46e0cd03-00000a67">
  <timeline>
    <DOMTimeline name="Bomb-omb Battle Field Mountain">
      <layers>
        <DOMLayer name="Layer 4" color="#FF4FFF">
          <frames>
            <DOMFrame index="0" keyMode="9728">
              <elements>
                <DOMGroup>
                  <members>
                    <DOMShape>
                      <fills>
                        <FillStyle index="1">
                          <BitmapFill bitmapPath="  Course Items-PL/ Decoration/ Signs &amp; Fences/Fence Repeat" bitmapIsClipped="false">
                            <matrix>
                              <Matrix a="20" d="20" tx="-863" ty="769.65"/>
                            </matrix>
                          </BitmapFill>
                        </FillStyle>
                      </fills>
                      <edges>
                        <Edge fillStyle0="1" edges="!-11809 15393|-17260 15393!-17260 15393|-17260 15733!-17260 15733|-11809 15733!-11809 15733|-11809 15393"/>
                      </edges>
                    </DOMShape>
                  </members>
                </DOMGroup>
                <DOMBitmapInstance libraryItemName="  Course Items-PL/ Decoration/ Vegetation/ Regular/Tree 64 Largeeer">
                  <matrix>
                    <Matrix tx="-934.35" ty="716.8"/>
                  </matrix>
                </DOMBitmapInstance>
                <DOMBitmapInstance libraryItemName="  Course Items-PL/ Decoration/ Vegetation/ Regular/Tree 64 Largeeer">
                  <matrix>
                    <Matrix tx="-583.4" ty="716.8"/>
                  </matrix>
                </DOMBitmapInstance>
                <DOMBitmapInstance libraryItemName="  Course Items-PL/ Decoration/ Vegetation/ Regular/Tree 64 Largeeer">
                  <matrix>
                    <Matrix tx="-230.45" ty="430.75"/>
                  </matrix>
                </DOMBitmapInstance>
                <DOMBitmapInstance libraryItemName="  Course Items-PL/ Decoration/ Vegetation/ Regular/Tree 64 Largeeer">
                  <matrix>
                    <Matrix tx="-550.4" ty="271.8"/>
                  </matrix>
                </DOMBitmapInstance>
                <DOMBitmapInstance libraryItemName="  Course Items-PL/ Decoration/ Vegetation/ Regular/Tree 64 Largeeer">
                  <matrix>
                    <Matrix tx="82.6" ty="-88.2"/>
                  </matrix>
                </DOMBitmapInstance>
                <DOMBitmapInstance libraryItemName="  Course Items-PL/ Decoration/ Vegetation/ Regular/Tree 64 Largeeer">
                  <matrix>
                    <Matrix tx="-715.35" ty="-235.15"/>
                  </matrix>
                </DOMBitmapInstance>
                <DOMGroup>
                  <members>
                    <DOMShape>
                      <fills>
                        <FillStyle index="1">
                          <BitmapFill bitmapPath="  Course Items-PL/ Decoration/ Signs &amp; Fences/Fence Repeat" bitmapIsClipped="false">
                            <matrix>
                              <Matrix a="20" d="20" tx="233.85" ty="119.3"/>
                            </matrix>
                          </BitmapFill>
                        </FillStyle>
                      </fills>
                      <edges>
                        <Edge fillStyle0="1" edges="!7967 2386|4677 2386!4677 2386|4677 2726!4677 2726|7967 2726!7967 2726|7967 2386"/>
                      </edges>
                    </DOMShape>
                  </members>
                </DOMGroup>
              </elements>
            </DOMFrame>
          </frames>
        </DOMLayer>
        <DOMLayer name="Layer 2" color="#9933CC" current="true" isSelected="true">
          <frames>
            <DOMFrame index="0" keyMode="9728">
              <elements>
                <DOMBitmapInstance libraryItemName="  Course Items-PL/ Decoration/ Vegetation/ Regular/Tree 64">
                  <matrix>
                    <Matrix tx="-861.2" ty="740.05"/>
                  </matrix>
                </DOMBitmapInstance>
                <DOMBitmapInstance libraryItemName="  Course Items-PL/ Decoration/ Vegetation/ Regular/Tree 64">
                  <matrix>
                    <Matrix tx="-681.2" ty="740.05"/>
                  </matrix>
                </DOMBitmapInstance>
                <DOMBitmapInstance libraryItemName="  Course Items-PL/ Decoration/ Vegetation/ Regular/Tree 64">
                  <matrix>
                    <Matrix tx="-72.7" ty="455"/>
                  </matrix>
                </DOMBitmapInstance>
                <DOMBitmapInstance libraryItemName="  Course Items-PL/ Decoration/ Vegetation/ Regular/Tree 64">
                  <matrix>
                    <Matrix tx="168.7" ty="-64.1"/>
                  </matrix>
                </DOMBitmapInstance>
                <DOMSymbolInstance libraryItemName="  Course Clips/ 1 - Bob-omb Battlefield/ Area 1-4/Bowling Ball Animation" selected="true">
                  <matrix>
                    <Matrix tx="276.9" ty="-443.9"/>
                  </matrix>
                  <transformationPoint>
                    <Point/>
                  </transformationPoint>
                  <Actionscript>
                    <script><![CDATA[onClipEvent (load) {
	gotoAndPlay(200);
}
]]></script>
                  </Actionscript>
                </DOMSymbolInstance>
                <DOMSymbolInstance libraryItemName="  Course Clips/ 1 - Bob-omb Battlefield/ Area 1-4/1-Bowling Ball Animation 2">
                  <matrix>
                    <Matrix tx="-150.8" ty="-92.95"/>
                  </matrix>
                  <transformationPoint>
                    <Point/>
                  </transformationPoint>
                  <Actionscript>
                    <script><![CDATA[onClipEvent (load) {
	gotoAndPlay(300);
}
]]></script>
                  </Actionscript>
                </DOMSymbolInstance>
                <DOMSymbolInstance libraryItemName="  Course Clips/ 1 - Bob-omb Battlefield/ Area 1-4/1- Bowling Ball 3">
                  <matrix>
                    <Matrix tx="761.7" ty="730"/>
                  </matrix>
                  <transformationPoint>
                    <Point/>
                  </transformationPoint>
                </DOMSymbolInstance>
              </elements>
            </DOMFrame>
          </frames>
        </DOMLayer>
        <DOMLayer name="Layer 3" color="#FFFF4F">
          <frames>
            <DOMFrame index="0" keyMode="9728">
              <elements>
                <DOMShape>
                  <fills>
                    <FillStyle index="1">
                      <SolidColor/>
                    </FillStyle>
                  </fills>
                  <strokes>
                    <StrokeStyle index="1">
                      <SolidStroke scaleMode="normal">
                        <fill>
                          <SolidColor color="#333333"/>
                        </fill>
                      </SolidStroke>
                    </StrokeStyle>
                  </strokes>
                  <edges>
                    <Edge fillStyle1="1" strokeStyle="1" edges="!5878 -9212|5878 -8512!5878 -8512|5178 -8512!5178 -8512|5178 -9212!5178 -9212|5878 -9212!12434 14540|12434 15240!12434 15240|11734 15240!11734 15240|11734 14540!11734 14540|12434 14540!-3360 -2213|-2660 -2213!-2660 -2213|-2660 -1513!-2660
 -1513|-3360 -1513!-3360 -1513|-3360 -2213"/>
                  </edges>
                </DOMShape>
              </elements>
            </DOMFrame>
          </frames>
        </DOMLayer>
        <DOMLayer name="Layer 1" color="#4FFF4F">
          <frames>
            <DOMFrame index="0" keyMode="9728">
              <elements>
                <DOMShape>
                  <fills>
                    <FillStyle index="1">
                      <SolidColor/>
                    </FillStyle>
                  </fills>
                  <strokes>
                    <StrokeStyle index="1">
                      <SolidStroke scaleMode="normal">
                        <fill>
                          <SolidColor color="#333333"/>
                        </fill>
                      </SolidStroke>
                    </StrokeStyle>
                  </strokes>
                  <edges>
                    <Edge fillStyle1="1" strokeStyle="1" edges="
!5878 -8512|5178 -8512!5178 -8512|5178 -9212!5178 -9212|5878 -9212!5878 -9212|5878 -8512!12434 15240|11734 15240!11734 15240|11734 14540!11734 14540|12434 14540!12434 14540|12434 15240!-3360 -2213|-2660 -2213!-2660 -2213|-2660 -1513!-2660
 -1513|-3360 -1513!-3360 -1513|-3360 -2213"/>
                  </edges>
                </DOMShape>
                <DOMSymbolInstance libraryItemName="  Course Clips/ 1 - Bob-omb Battlefield/ Area 1-4/1- DarkestER Ground">
                  <matrix>
                    <Matrix tx="248.9" ty="-298.15"/>
                  </matrix>
                  <transformationPoint>
                    <Point y="-0.05"/>
                  </transformationPoint>
                  <color>
                    <Color tintMultiplier="0.5"/>
                  </color>
                </DOMSymbolInstance>
                <DOMSymbolInstance libraryItemName="  Course Clips/ 1 - Bob-omb Battlefield/ Area 1-4/1- Darkerest Ground">
                  <matrix>
                    <Matrix tx="-152.35" ty="-187.75"/>
                  </matrix>
                  <transformationPoint>
                    <Point x="-0.2" y="0.2"/>
                  </transformationPoint>
                  <color>
                    <Color tintMultiplier="0.4"/>
                  </color>
                </DOMSymbolInstance>
                <DOMSymbolInstance libraryItemName="  Course Clips/ 1 - Bob-omb Battlefield/ Area 1-4/1-Darkest Ground">
                  <matrix>
                    <Matrix tx="138.95" ty="110.55"/>
                  </matrix>
                  <transformationPoint>
                    <Point x="-0.25" y="0.2"/>
                  </transformationPoint>
                  <color>
                    <Color tintMultiplier="0.3"/>
                  </color>
                </DOMSymbolInstance>
                <DOMSymbolInstance libraryItemName="  Course Clips/ 1 - Bob-omb Battlefield/ Area 1-4/1- Draker ground 2">
                  <matrix>
                    <Matrix tx="-438" ty="618.55"/>
                  </matrix>
                  <transformationPoint>
                    <Point x="-0.25" y="0.2"/>
                  </transformationPoint>
                  <color>
                    <Color tintMultiplier="0.2"/>
                  </color>
                </DOMSymbolInstance>
                <DOMSymbolInstance libraryItemName="  Course Clips/ 1 - Bob-omb Battlefield/ Area 1-4/1- Dark Gound 2">
                  <matrix>
                    <Matrix tx="-212.05" ty="615.8"/>
                  </matrix>
                  <transformationPoint>
                    <Point x="0.25"/>
                  </transformationPoint>
                  <color>
                    <Color tintMultiplier="0.1"/>
                  </color>
                </DOMSymbolInstance>
                <DOMGroup>
                  <members>
                    <DOMShape>
                      <fills>
                        <FillStyle index="1">
                          <BitmapFill bitmapPath="  Course Items-PL/ Ground/ Grassy Ground/Light Ground Big" bitmapIsClipped="false">
                            <matrix>
                              <Matrix a="20" d="20" tx="3021.05" ty="-443"/>
                            </matrix>
                          </BitmapFill>
                        </FillStyle>
                      </fills>
                      <edges>
                        <Edge fillStyle0="1" edges="
!23774 -17259|17423 12517!17423 12517|21498 12517!21498 12517|25510 -17339!25510 -17339|23774 -17259!6624 14146.5[#136A.07 #37A5.E7 3316 14133!3316 14133|-8360 16096!-8360 16096|-25474 16096!-25474 16096|-25474 18821!-25474 18821|20837
 18821!20837 18821|20837 17342!20837 17342|21274 14097!21274 14097|17061 14096.5!17061 14096.5|17053 14133!17053 14133|15541 15135!15541 15135|15541 15136!15541 15136|11971 15616!11971 15616|8983 15176!8983 15176|6624 14146.5"/>
                      </edges>
                    </DOMShape>
                  </members>
                </DOMGroup>
                <DOMBitmapInstance libraryItemName="  Course Items-PL/ Blocks, Tiles &amp; Other Textures/ Rocks &amp; Blocks (Tiled)/Mossy Rock">
                  <matrix>
                    <Matrix tx="-778.65" ty="515.2"/>
                  </matrix>
                </DOMBitmapInstance>
                <DOMBitmapInstance libraryItemName="  Course Items-PL/ Blocks, Tiles &amp; Other Textures/ Rocks &amp; Blocks (Tiled)/Mossy Rock">
                  <matrix>
                    <Matrix tx="207" ty="659.8"/>
                  </matrix>
                </DOMBitmapInstance>
                <DOMGroup>
                  <members>
                    <DOMShape>
                      <fills>
                        <FillStyle index="1">
                          <BitmapFill bitmapPath="  Course Items-PL/ Ground/ Grassy Ground/Grass Chunk x32 Bit" bitmapIsClipped="false">
                            <matrix>
                              <Matrix a="20" d="20" tx="-1968.05" ty="691.8"/>
                            </matrix>
                          </BitmapFill>
                        </FillStyle>
                      </fills>
                      <edges>
                        <Edge fillStyle0="1" edges="
!6235 14264[6438 14264 6655 14265!6655 14265[6637 14257 6619 14250!6619 14250|6775 13887!6775 13887|6775 13836!6775 13836|3386 13836!3386 13836|3386 14253!3386 14253[3959 14261 6235 14264"/>
                      </edges>
                    </DOMShape>
                  </members>
                </DOMGroup>
                <DOMGroup>
                  <members>
                    <DOMShape>
                      <fills>
                        <FillStyle index="1">
                          <BitmapFill bitmapPath="  Course Items-PL/ Ground/ Grassy Ground/Grass Chunk x32 Bit" bitmapIsClipped="false">
                            <matrix>
                              <Matrix a="4.23980712890625" b="-19.5419311523438" c="19.5419311523438" d="4.23980712890625" tx="706.1" ty="1333.8"/>
                            </matrix>
                          </BitmapFill>
                        </FillStyle>
                      </fills>
                      <edges>
                        <Edge fillStyle0="1" edges="
!23672 -17343|17194 12517!17194 12517|17603 12517!17603 12517|23819 -16875!23819 -16875|23672 -17343"/>
                      </edges>
                    </DOMShape>
                  </members>
                </DOMGroup>
                <DOMGroup>
                  <members>
                    <DOMShape>
                      <fills>
                        <FillStyle index="1">
                          <BitmapFill bitmapPath="  Course Items-PL/ Ground/ Grassy Ground/Grass Chunk x32 Bit" bitmapIsClipped="false">
                            <matrix>
                              <Matrix a="19.71435546875" b="-3.30352783203125" c="3.30352783203125" d="19.71435546875" tx="-1790.45" ty="1020.1"/>
                            </matrix>
                          </BitmapFill>
                        </FillStyle>
                      </fills>
                      <edges>
                        <Edge fillStyle0="1" edges="
!3372 13836|-8170 15770!-8170 15770|-8170 16193!-8170 16193|3440 14247!3440 14247|3372 13836"/>
                      </edges>
                    </DOMShape>
                  </members>
                </DOMGroup>
                <DOMGroup>
                  <members>
                    <DOMShape>
                      <fills>
                        <FillStyle index="1">
                          <BitmapFill bitmapPath="  Course Items-PL/ Ground/ Grassy Ground/Grass Chunk x32 Bit" bitmapIsClipped="false">
                            <matrix>
                              <Matrix a="20" d="20" tx="-3060.9" ty="786.8"/>
                            </matrix>
                          </BitmapFill>
                        </FillStyle>
                      </fills>
                      <edges>
                        <Edge fillStyle0="1" edges="
!-8061 15736|-25509 15736!-25509 15736|-25509 16153!-25509 16153|-8061 16153!-8061 16153|-8061 15736"/>
                      </edges>
                    </DOMShape>
                  </members>
                </DOMGroup>
                <DOMGroup>
                  <members>
                    <DOMShape>
                      <fills>
                        <FillStyle index="1">
                          <BitmapFill bitmapPath="  Course Items-PL/ Ground/ Grassy Ground/Grass Chunk x32 Bit" bitmapIsClipped="false">
                            <matrix>
                              <Matrix a="17.2938690185547" b="-9.91600036621094" c="9.91600036621094" d="17.2938690185547" tx="-1457.05" ty="2020.9"/>
                            </matrix>
                          </BitmapFill>
                        </FillStyle>
                      </fills>
                      <edges>
                        <Edge fillStyle0="1" edges="
!15705 15200[16256 14884 16845 14546!16845 14546[16848 14544 16965 14457!16965 14457[17038 14403 17156 14315!17156 14315[17165 14308 17354 14181!17354 14181|16924 14011!16924 14011|16994 13965!16994 13965|15454 14847!15454 14847|15485
 14919!15485 14919|15705 15200"/>
                      </edges>
                    </DOMShape>
                  </members>
                </DOMGroup>
                <DOMGroup>
                  <members>
                    <DOMShape>
                      <fills>
                        <FillStyle index="1">
                          <BitmapFill bitmapPath="  Course Items-PL/ Ground/ Grassy Ground/Grass Chunk x32 Bit" bitmapIsClipped="false">
                            <matrix>
                              <Matrix a="19.8299713134766" b="-2.26567077636719" c="2.26567077636719" d="19.8299713134766" tx="-1957.05" ty="1054.4"/>
                            </matrix>
                          </BitmapFill>
                        </FillStyle>
                      </fills>
                      <edges>
                        <Edge fillStyle0="1" edges="
!15485 14919|15471 14885!15471 14885|15446 14851!15446 14851|11975 15248!11975 15248|11975 15668!11975 15668[11971 15667 11967 15667!11967 15667|11966 15689!11966 15689[12717 15596 13393 15519!13393 15519[14395 15404 15695 15199!15695
 15199|15485 14919"/>
                      </edges>
                    </DOMShape>
                  </members>
                </DOMGroup>
                <DOMGroup>
                  <members>
                    <DOMShape>
                      <fills>
                        <FillStyle index="1">
                          <BitmapFill bitmapPath="  Course Items-PL/ Ground/ Grassy Ground/Grass Chunk x32 Bit" bitmapIsClipped="false">
                            <matrix>
                              <Matrix a="19.7677917480469" b="2.876953125" c="-2.876953125" d="19.7677917480469" tx="-1949.05" ty="390.8"/>
                            </matrix>
                          </BitmapFill>
                        </FillStyle>
                      </fills>
                      <edges>
                        <Edge fillStyle0="1" edges="
!9031 15239[10353 15432 11967 15667!11967 15667[11971 15667 11975 15668!11975 15668|11975 15232!11975 15232|8910 14786!8910 14786|9031 15239"/>
                      </edges>
                    </DOMShape>
                  </members>
                </DOMGroup>
                <DOMGroup>
                  <members>
                    <DOMShape>
                      <fills>
                        <FillStyle index="1">
                          <BitmapFill bitmapPath="  Course Items-PL/ Ground/ Grassy Ground/Grass Chunk x32 Bit" bitmapIsClipped="false">
                            <matrix>
                              <Matrix a="18.349609375" b="7.89520263671875" c="-7.89520263671875" d="18.349609375" tx="-1777" ty="-217.85"/>
                            </matrix>
                          </BitmapFill>
                        </FillStyle>
                      </fills>
                      <edges>
                        <Edge fillStyle1="1" edges="
!6655 14265[6637 14257 6619 14250!6619 14250|6789 13856!6789 13856|8915 14771!8915 14771|8915 14787!8915 14787|8910 14786!8910 14786|9015 15220!9015 15220[8394 15015 7922 14812!7922 14812[7427 14598 6986 14408!6986 14408[6816 14334 6655
 14265"/>
                      </edges>
                    </DOMShape>
                  </members>
                </DOMGroup>
                <DOMBitmapInstance libraryItemName="  Course Items-PL/ Various Platforms/ Non-Coded PL/ Coded PL Bits/YI Log Side">
                  <matrix>
                    <Matrix tx="-332.05" ty="-96.15"/>
                  </matrix>
                </DOMBitmapInstance>
                <DOMGroup>
                  <members>
                    <DOMShape>
                      <fills>
                        <FillStyle index="1">
                          <BitmapFill bitmapPath="  Course Items-PL/ Blocks, Tiles &amp; Other Textures/ Bricks &amp; Woods/Wood Block" bitmapIsClipped="false">
                            <matrix>
                              <Matrix a="0" b="20" c="-20" d="0" tx="-275.85" ty="447.2"/>
                            </matrix>
                          </BitmapFill>
                        </FillStyle>
                        <FillStyle index="2">
                          <BitmapFill bitmapPath="  Course Items-PL/ Blocks, Tiles &amp; Other Textures/ Bricks &amp; Woods/Wood Block" bitmapIsClipped="false">
                            <matrix>
                              <Matrix a="20" d="20" tx="-307.85" ty="444.7"/>
                            </matrix>
                          </BitmapFill>
                        </FillStyle>
                      </fills>
                      <strokes>
                        <StrokeStyle index="1">
                          <SolidStroke scaleMode="normal">
                            <fill>
                              <SolidColor/>
                            </fill>
                          </SolidStroke>
                        </StrokeStyle>
                      </strokes>
                      <edges>
                        <Edge fillStyle1="1" strokeStyle="1" edges="
!-6789 9596|-7049 9596!-7049 9596|-7049 8996!-7049 8996|-6409 8996!-6409 8996|-6409 9596!-6409 9596|-6669 9596"/>
                        <Edge fillStyle1="2" strokeStyle="1" edges="
!-6669 9596|-6669 10047!-6669 10047|-6789 10047!-6789 10047|-6789 9596"/>
                        <Edge fillStyle0="2" fillStyle1="1" strokeStyle="1" edges="
!-6669 9596|-6789 9596"/>
                      </edges>
                    </DOMShape>
                    <DOMSymbolInstance libraryItemName="  Course Items-PL/ Decoration/ Signs &amp; Fences/ Coded Sign/Sign Image Clip" selected="true">
                      <matrix>
                        <Matrix tx="-336.45" ty="464.9"/>
                      </matrix>
                      <transformationPoint>
                        <Point/>
                      </transformationPoint>
                    </DOMSymbolInstance>
                    <DOMGroup selected="true">
                      <members>
                        <DOMShape selected="true">
                          <fills>
                            <FillStyle index="1">
                              <SolidColor color="#FFFFFF" alpha="0.333333333333333"/>
                            </FillStyle>
                          </fills>
                          <edges>
                            <Edge fillStyle1="1" edges="
!-6979 9056S2|-6479 9056!-6479 9056|-6479 9536!-6479 9536|-6979 9536!-6979 9536|-6979 9056"/>
                          </edges>
                        </DOMShape>
                      </members>
                    </DOMGroup>
                  </members>
                </DOMGroup>
                <DOMGroup>
                  <members>
                    <DOMShape>
                      <fills>
                        <FillStyle index="1">
                          <BitmapFill bitmapPath="  Course Items-PL/ Blocks, Tiles &amp; Other Textures/ Bricks &amp; Woods/Wood Block" bitmapIsClipped="false">
                            <matrix>
                              <Matrix a="0" b="20" c="-20" d="0" tx="-56.4" ty="447.2"/>
                            </matrix>
                          </BitmapFill>
                        </FillStyle>
                        <FillStyle index="2">
                          <BitmapFill bitmapPath="  Course Items-PL/ Blocks, Tiles &amp; Other Textures/ Bricks &amp; Woods/Wood Block" bitmapIsClipped="false">
                            <matrix>
                              <Matrix a="20" d="20" tx="-88.4" ty="444.7"/>
                            </matrix>
                          </BitmapFill>
                        </FillStyle>
                      </fills>
                      <strokes>
                        <StrokeStyle index="1">
                          <SolidStroke scaleMode="normal">
                            <fill>
                              <SolidColor/>
                            </fill>
                          </SolidStroke>
                        </StrokeStyle>
                      </strokes>
                      <edges>
                        <Edge fillStyle1="1" strokeStyle="1" edges="
!-2400 9596|-2660 9596!-2660 9596|-2660 8996!-2660 8996|-2020 8996!-2020 8996|-2020 9596!-2020 9596|-2280 9596"/>
                        <Edge fillStyle1="2" strokeStyle="1" edges="
!-2280 9596|-2280 10047!-2280 10047|-2400 10047!-2400 10047|-2400 9596"/>
                        <Edge fillStyle0="2" fillStyle1="1" strokeStyle="1" edges="
!-2280 9596|-2400 9596"/>
                      </edges>
                    </DOMShape>
                    <DOMSymbolInstance libraryItemName="  Course Items-PL/ Decoration/ Signs &amp; Fences/ Coded Sign/Sign Image Clip" selected="true">
                      <matrix>
                        <Matrix tx="-117" ty="464.9"/>
                      </matrix>
                      <transformationPoint>
                        <Point/>
                      </transformationPoint>
                    </DOMSymbolInstance>
                    <DOMGroup selected="true">
                      <members>
                        <DOMShape selected="true">
                          <fills>
                            <FillStyle index="1">
                              <SolidColor color="#FFFFFF" alpha="0.333333333333333"/>
                            </FillStyle>
                          </fills>
                          <edges>
                            <Edge fillStyle1="1" edges="
!-2590 9056S2|-2090 9056!-2090 9056|-2090 9536!-2090 9536|-2590 9536!-2590 9536|-2590 9056"/>
                          </edges>
                        </DOMShape>
                      </members>
                    </DOMGroup>
                  </members>
                </DOMGroup>
                <DOMSymbolInstance libraryItemName="  Course Clips/ 1 - Bob-omb Battlefield/ Area 1-4/1-4 Dark Ground">
                  <matrix>
                    <Matrix tx="970.45" ty="664.9"/>
                  </matrix>
                  <transformationPoint>
                    <Point/>
                  </transformationPoint>
                  <color>
                    <Color tintMultiplier="0.05"/>
                  </color>
                </DOMSymbolInstance>
              </elements>
            </DOMFrame>
          </frames>
        </DOMLayer>
      </layers>
    </DOMTimeline>
  </timeline>
</DOMSymbolItem>